proto_ros/__init__.py
proto_ros/msg2proto.py
proto_ros/proto2msg.py
proto_ros/protoc_gen_json.py
proto_ros/protoc_gen_msg.py
proto_ros-0.1.0.dist-info/LICENSE
proto_ros-0.1.0.dist-info/METADATA
proto_ros-0.1.0.dist-info/WHEEL
proto_ros-0.1.0.dist-info/entry_points.txt
proto_ros-0.1.0.dist-info/top_level.txt
proto_ros-0.1.0.dist-info/RECORD
