Metadata-Version: 2.1
Name: proto_ros
Version: 0.1.0
Summary: Translations between Protobuf and ROS message definitions
Author-email: Eric Dortmans <eric.dortmans@gmail.com>
Project-URL: source, https://github.com/dortmans/proto_ros
Keywords: protobuf,proto,ros,msg,translation,parser,grammar
Classifier: Development Status :: 3 - Alpha
Classifier: Intended Audience :: Science/Research
Classifier: License :: OSI Approved :: MIT License
Classifier: Natural Language :: English
Classifier: Operating System :: OS Independent
Classifier: Programming Language :: Python :: 3.8
Classifier: Topic :: Scientific/Engineering
Requires-Python: >=3.8
License-File: LICENSE
Requires-Dist: numpy >=1.24.1
Requires-Dist: parsimonious >=0.10.0
Requires-Dist: protobuf >=3.6.1
